python_forex_quotes.py
python_forex_quotes-2.0.3.dist-info/LICENSE.md
python_forex_quotes-2.0.3.dist-info/METADATA
python_forex_quotes-2.0.3.dist-info/WHEEL
python_forex_quotes-2.0.3.dist-info/top_level.txt
python_forex_quotes-2.0.3.dist-info/RECORD
